seneca/.version
seneca/__init__.py
seneca/client.py
seneca/config.py
seneca/exceptions.py
seneca/logger.py
seneca/ast/__init__.py
seneca/ast/compiler.py
seneca/ast/linter.py
seneca/ast/whitelists.py
seneca/contracts/__init__.py
seneca/contracts/curreny.s.py
seneca/contracts/submission.s.py
seneca/db/__init__.py
seneca/db/contract.py
seneca/db/driver.py
seneca/db/encoder.py
seneca/db/orm.py
seneca/db/cr/__init__.py
seneca/db/cr/cache.py
seneca/db/cr/client.py
seneca/db/cr/transaction_bag.py
seneca/execution/__init__.py
seneca/execution/executor.py
seneca/execution/module.py
seneca/execution/runtime.py
seneca/execution/metering/__init__.py
seneca/execution/metering/estimator.py
seneca/execution/metering/resource.py
seneca/execution/metering/tracer.c
seneca/execution/metering/tracer.cpython-36m-darwin.so
seneca/stdlib/__init__.py
seneca/stdlib/env.py
tests/__init__.py
tests/run.py
tests/utils.py
tests/integration/__init__.py
tests/integration/test_atomic_swap.py
tests/integration/test_complex_contracts.py
tests/integration/test_executor_submission_process.py
tests/integration/test_senecaCompiler_integration.py
tests/integration/test_seneca_client_replaces_executor.py
tests/integration/test_contracts/__init__.py
tests/integration/test_contracts/atomic_swaps.s.py
tests/integration/test_contracts/bad_time.s.py
tests/integration/test_contracts/currency.s.py
tests/integration/test_contracts/erc20_clone.s.py
tests/integration/test_contracts/i_use_env.s.py
tests/integration/test_contracts/import_this.s.py
tests/integration/test_contracts/importing_that.s.py
tests/integration/test_contracts/json_tests.s.py
tests/integration/test_contracts/leaky.s.py
tests/integration/test_contracts/test_client.py
tests/integration/test_contracts/test_construct_function_works.s.py
tests/integration/test_contracts/test_hashing_works.s.py
tests/integration/test_contracts/test_orm_foreign_hash_contract.s.py
tests/integration/test_contracts/test_orm_foreign_key_contract.s.py
seneca-0.6.0.dist-info/LICENSE
seneca-0.6.0.dist-info/METADATA
seneca-0.6.0.dist-info/WHEEL
seneca-0.6.0.dist-info/top_level.txt
seneca-0.6.0.dist-info/zip-safe
seneca-0.6.0.dist-info/RECORD
